reference_package/__init__.py
reference_package/api/__init__.py
reference_package/api/internal.py
reference_package/api/public.py
reference_package/cli/__init__.py
reference_package/cli/example.py
reference_package/lib/__init__.py
reference_package/lib/constants.py
reference_package/lib/example.py
reference_package-0.6.4.dist-info/licenses/LICENSE
reference_package-0.6.4.dist-info/METADATA
reference_package-0.6.4.dist-info/WHEEL
reference_package-0.6.4.dist-info/entry_points.txt
reference_package-0.6.4.dist-info/top_level.txt
reference_package-0.6.4.dist-info/RECORD
