Metadata-Version: 2.4
Name: reference_package
Version: 0.6.4
Summary: A basic package setup with examples.
Author: Kaleb Coberly
Maintainer-email: kaleb.coberly@gmail.com
Requires-Python: >=3.12
License-File: LICENSE
Requires-Dist: click
Requires-Dist: comb_utils
Requires-Dist: typeguard
Requires-Dist: ipython<9.8.0,>=8.22.0
Requires-Dist: matplotlib<3.11.0,>=3.9.0
Requires-Dist: networkx<3.7.0,>=3.3.0
Requires-Dist: numpy<2.4.0,>=2.0.0
Requires-Dist: pandas<2.4.0,>=2.3.0
Requires-Dist: scikit-image<0.26.0,>=0.23.0
Requires-Dist: scikit-learn<1.8.0,>=1.5.0
Requires-Dist: scipy<1.17.0,>=1.13.0
Requires-Dist: xarray<2025.12.0,>=2024.3.0
Requires-Dist: zarr<3.2.0,>=2.18.0
Provides-Extra: dev
Requires-Dist: reference_package[build]; extra == "dev"
Requires-Dist: reference_package[doc]; extra == "dev"
Requires-Dist: reference_package[qc]; extra == "dev"
Requires-Dist: reference_package[test]; extra == "dev"
Provides-Extra: build
Requires-Dist: build; extra == "build"
Requires-Dist: twine; extra == "build"
Requires-Dist: wheel; extra == "build"
Provides-Extra: doc
Requires-Dist: furo; extra == "doc"
Requires-Dist: sphinx; extra == "doc"
Requires-Dist: sphinx-autodoc-typehints; extra == "doc"
Requires-Dist: sphinx-click; extra == "doc"
Provides-Extra: qc
Requires-Dist: bandit; extra == "qc"
Requires-Dist: black; extra == "qc"
Requires-Dist: flake8; extra == "qc"
Requires-Dist: flake8-annotations; extra == "qc"
Requires-Dist: flake8-bandit; extra == "qc"
Requires-Dist: flake8-black; extra == "qc"
Requires-Dist: flake8-bugbear; extra == "qc"
Requires-Dist: flake8-docstrings; extra == "qc"
Requires-Dist: flake8-isort; extra == "qc"
Requires-Dist: isort; extra == "qc"
Requires-Dist: jake; extra == "qc"
Requires-Dist: pytype; python_version < "3.13" and extra == "qc"
Requires-Dist: reference_package[test]; extra == "qc"
Requires-Dist: safety; extra == "qc"
Provides-Extra: test
Requires-Dist: coverage[toml]; extra == "test"
Requires-Dist: pytest; extra == "test"
Requires-Dist: pytest-cov; extra == "test"
Dynamic: license-file
